[
    {"name": "Alice"},
    {"name": "Bob"},
    {"name": "Charlie"},
    {"name": "David"},
    {"name": "Eva"},
    {"name": "Frank"},
    {"name": "Grace"},
    {"name": "Henry"},
    {"name": "Ivy"},
    {"name": "Jack"},
    {"name": "Katherine"},
    {"name": "Liam"},
    {"name": "Mia"},
    {"name": "Noah"},
    {"name": "Olivia"},
    {"name": "Peter"},
    {"name": "Quinn"},
    {"name": "Rachel"},
    {"name": "Samuel"},
    {"name": "Tina"},
    {"name": "Ulysses"},
    {"name": "Violet"},
    {"name": "William"},
    {"name": "Xander"},
    {"name": "Yvonne"},
    {"name": "Zane"},
    {"name": "Abigail"},
    {"name": "Benjamin"},
    {"name": "Catherine"},
    {"name": "Daniel"},
    {"name": "Emily"},
    {"name": "Fiona"},
    {"name": "George"},
    {"name": "Hannah"},
    {"name": "Isaac"},
    {"name": "Jessica"},
    {"name": "Kevin"},
    {"name": "Lily"},
    {"name": "Michael"}
  ]
  